metawork/__init__.py
metawork/code_meta.py
metawork/doc_meta.py
metawork/fs_meta.py
metawork/media_meta.py
metawork/utils.py
metawork-0.1.1.dist-info/licenses/LICENSE
tests/__init__.py
tests/test_code_meta.py
metawork-0.1.1.dist-info/METADATA
metawork-0.1.1.dist-info/WHEEL
metawork-0.1.1.dist-info/top_level.txt
metawork-0.1.1.dist-info/RECORD
