Metadata-Version: 2.4
Name: metawork
Version: 0.1.1
Summary: Biblioteca para manipulação de metadados em arquivos de código, documentos e mídias.
Author: Pedro Richil
Author-email: pedrorichillbia@gmail.com
Classifier: Programming Language :: Python :: 3
Classifier: License :: OSI Approved :: MIT License
License-File: LICENSE
Requires-Dist: python-docx
Requires-Dist: openpyxl
Requires-Dist: Pillow
Requires-Dist: piexif
Requires-Dist: mutagen
Requires-Dist: PyPDF2
Dynamic: author
Dynamic: author-email
Dynamic: classifier
Dynamic: license-file
Dynamic: requires-dist
Dynamic: summary
